.gitignore
AUTHORS
LICENSE
MANIFEST.in
README.rst
VERSION
runtests.py
setup.py
tox.ini
django_labjs.egg-info/PKG-INFO
django_labjs.egg-info/SOURCES.txt
django_labjs.egg-info/dependency_links.txt
django_labjs.egg-info/not-zip-safe
django_labjs.egg-info/requires.txt
django_labjs.egg-info/top_level.txt
labJS/__init__.py
labJS/base.py
labJS/conf.py
labJS/models.py
labJS/tests.py
labJS/static/labjs/LAB-debug.min.js
labJS/static/labjs/LAB.js
labJS/static/labjs/LAB.min.js
labJS/static/labjs/LAB.src.js
labJS/templates/labjs/header.html
labJS/templates/labjs/labjs.html
labJS/templates/labjs/wait.html
labJS/templatetags/__init__.py
labJS/templatetags/labjs.py
test_project/__init__.py
test_project/settings.py
test_project/urls.py
test_project/wsgi.py