Metadata-Version: 1.1
Name: django-labjs
Version: 0.2.0
Summary: Django labjs templatetags.
Home-page: https://github.com/lpomfrey/django-labjs
Author: Luke Pomfrey
Author-email: lpomfrey@gmail.com
License: UNKNOWN
Platform: UNKNOWN
Classifier: Development Status :: 4 - Beta
Classifier: Environment :: Web Environment
Classifier: Framework :: Django
Classifier: Intended Audience :: Developers
Classifier: License :: OSI Approved :: BSD License
Classifier: Operating System :: OS Independent
Classifier: Programming Language :: Python
Classifier: Topic :: Software Development :: Libraries :: Python Modules
